abac/__init__.py
abac/abac_manager.py
abac/abac_pip.py
abac/pdp.py
research_access_abac-1.0.5.dist-info/METADATA
research_access_abac-1.0.5.dist-info/WHEEL
research_access_abac-1.0.5.dist-info/top_level.txt
research_access_abac-1.0.5.dist-info/RECORD
