Metadata-Version: 2.1
Name: research-access-abac
Version: 1.0.5
Summary: Implementation of ABAC for research data files
Home-page: UNKNOWN
Author: Catherine Nyambura, Eddy Mwenda
Author-email: UNKNOWN
License: UNKNOWN
Platform: UNKNOWN
Requires-Dist: backcall (==0.1.0)
Requires-Dist: decorator (==4.4.0)
Requires-Dist: ipython (==7.6.1)
Requires-Dist: ipython-genutils (==0.2.0)
Requires-Dist: jedi (==0.14.1)
Requires-Dist: jsonpickle (==1.2)
Requires-Dist: parso (==0.5.1)
Requires-Dist: pexpect (==4.7.0)
Requires-Dist: pickleshare (==0.7.5)
Requires-Dist: prompt-toolkit (==2.0.9)
Requires-Dist: ptyprocess (==0.6.0)
Requires-Dist: Pygments (==2.4.2)
Requires-Dist: pymongo (==3.7.2)
Requires-Dist: Pyro4 (==4.75)
Requires-Dist: serpent (==1.28)
Requires-Dist: six (==1.12.0)
Requires-Dist: traitlets (==4.3.2)
Requires-Dist: vakt (==1.2.1)
Requires-Dist: virtualenv (==16.6.0)
Requires-Dist: wcwidth (==0.1.7)
